<?xml version="1.0" encoding="UTF8"?>
<RESULTS>
  <ROW>
    <COLUMN NAME="USER_ID">
      <![CDATA[1]]>
    </COLUMN>
    <COLUMN NAME="STARTS">
      <![CDATA[2]]>
    </COLUMN>
    <COLUMN NAME="CANCELS">
      <![CDATA[1]]>
    </COLUMN>
    <COLUMN NAME="PUBLISHES">
      <![CDATA[1]]>
    </COLUMN>
  </ROW>
  <ROW>
    <COLUMN NAME="USER_ID">
      <![CDATA[2]]>
    </COLUMN>
    <COLUMN NAME="STARTS">
      <![CDATA[1]]>
    </COLUMN>
    <COLUMN NAME="CANCELS">
      <![CDATA[0]]>
    </COLUMN>
    <COLUMN NAME="PUBLISHES">
      <![CDATA[1]]>
    </COLUMN>
  </ROW>
  <ROW>
    <COLUMN NAME="USER_ID">
      <![CDATA[3]]>
    </COLUMN>
    <COLUMN NAME="STARTS">
      <![CDATA[1]]>
    </COLUMN>
    <COLUMN NAME="CANCELS">
      <![CDATA[1]]>
    </COLUMN>
    <COLUMN NAME="PUBLISHES">
      <![CDATA[0]]>
    </COLUMN>
  </ROW>
  <ROW>
    <COLUMN NAME="USER_ID">
      <![CDATA[4]]>
    </COLUMN>
    <COLUMN NAME="STARTS">
      <![CDATA[1]]>
    </COLUMN>
    <COLUMN NAME="CANCELS">
      <![CDATA[0]]>
    </COLUMN>
    <COLUMN NAME="PUBLISHES">
      <![CDATA[0]]>
    </COLUMN>
  </ROW>
</RESULTS>
